README
rdfutils.py
setup.py
rdfutils.egg-info/PKG-INFO
rdfutils.egg-info/SOURCES.txt
rdfutils.egg-info/dependency_links.txt
rdfutils.egg-info/top_level.txt