Metadata-Version: 1.1
Name: rdfutils
Version: 0.1
Summary: Thin wrapper functions to work with an RDF store based on the Redland C library & Python bindings (python-librdf)
Home-page: http://git.constantvzw.org/aa.rdfutils.git
Author: Michael Murtaugh
Author-email: mm@automatist.net
License: GPL3
Keywords: rdf
Platform: UNKNOWN
Classifier: Development Status :: 3 - Alpha
Classifier: License :: OSI Approved :: GNU General Public License v3 or later (GPLv3+)
Classifier: Programming Language :: Python
Classifier: Topic :: Utilities
Classifier: Topic :: Text Processing :: Markup :: HTML
Classifier: Topic :: Database
Classifier: Topic :: Database :: Database Engines/Servers
Classifier: Topic :: Text Processing :: Indexing
